{"frameRate":24,"isGlobal":0,"armature":[{"defaultActions":[{"gotoAndPlay":"newAnimation"}],"ik":[],"type":"Armature","frameRate":24,"animation":[{"ffd":[],"playTimes":0,"ik":[],"duration":24,"frame":[],"bone":[{"rotateFrame":[{"duration":24}],"scaleFrame":[{"duration":24}],"name":"root","translateFrame":[{"duration":24}]},{"rotateFrame":[{"duration":24}],"scaleFrame":[{"y":1.4355,"tweenEasing":0,"duration":24,"x":1.3589},{"y":0.3356,"duration":0,"x":0.3945}],"name":"图层_4","translateFrame":[{"tweenEasing":0,"duration":2},{"y":8,"tweenEasing":0,"duration":2,"x":11.75},{"y":5,"tweenEasing":0,"duration":2,"x":0.4091},{"y":3,"tweenEasing":0,"duration":2,"x":11.75},{"y":-4,"tweenEasing":0,"duration":2,"x":0.4091},{"y":-2.45,"tweenEasing":0,"duration":2,"x":11.75},{"tweenEasing":0,"duration":2,"x":0.4091},{"y":6,"tweenEasing":0,"duration":2,"x":11.75},{"y":1,"tweenEasing":0,"duration":2,"x":4.4091},{"y":8,"tweenEasing":0,"duration":2,"x":11.75},{"y":-4,"tweenEasing":0,"duration":2,"x":21.2091},{"tweenEasing":0,"duration":2,"x":13.75},{"duration":0,"x":21}]},{"rotateFrame":[{"duration":24}],"scaleFrame":[{"y":1.4355,"tweenEasing":0,"duration":24,"x":1.3589},{"y":0.3284,"duration":0,"x":0.3429}],"name":"图层_3","translateFrame":[{"tweenEasing":0,"duration":24},{"duration":0,"x":-5}]}],"slot":[{"colorFrame":[{"tweenEasing":0,"color":{"aM":60},"duration":23},{"tweenEasing":0,"color":{"aM":75},"duration":1},{"color":{"aM":60},"duration":0}],"displayFrame":[{"duration":24}],"name":"外轮廓"},{"colorFrame":[{"tweenEasing":0,"color":{"aM":60},"duration":23},{"tweenEasing":0,"color":{"aM":75},"duration":1},{"color":{"aM":60},"duration":0}],"displayFrame":[{"duration":24}],"name":"眼珠"},{"colorFrame":[],"displayFrame":[],"name":"图层_3"},{"colorFrame":[],"displayFrame":[],"name":"图层_4"}],"name":"newAnimation"}],"bone":[{"name":"root","transform":{}},{"transform":{"y":-6,"scX":0.7829,"x":-17},"name":"图层_4","parent":"root"},{"transform":{"y":-10,"scX":0.7829,"x":31},"name":"图层_3","parent":"root"}],"aabb":{"width":543,"y":-183,"height":271,"x":-265.1601042786395},"slot":[{"name":"外轮廓","parent":"图层_3","color":{"aM":75}},{"z":1,"name":"眼珠","parent":"图层_4","color":{"aM":75}},{"z":2,"displayIndex":-1,"name":"图层_3","parent":"root","color":{}},{"z":3,"displayIndex":-1,"name":"图层_4","parent":"root","color":{}}],"name":"凝视惩罚","skin":[{"slot":[{"display":[{"path":"凝视惩罚/图层_3","type":"image","name":"凝视惩罚/图层_3","transform":{"y":-37.5,"x":-31.5}}],"name":"外轮廓"},{"display":[{"path":"凝视惩罚/图层_4","type":"image","name":"凝视惩罚/图层_4","transform":{"x":2}}],"name":"眼珠"}],"name":""}]}],"name":"凝视惩罚v2-2","version":"5.5"}